CHANGES.txt
CONTRIBUTORS.txt
MANIFEST.in
README.rst
setup.py
pyramid_dogpile_cache/__init__.py
pyramid_dogpile_cache/tests.py
pyramid_dogpile_cache.egg-info/PKG-INFO
pyramid_dogpile_cache.egg-info/SOURCES.txt
pyramid_dogpile_cache.egg-info/dependency_links.txt
pyramid_dogpile_cache.egg-info/entry_points.txt
pyramid_dogpile_cache.egg-info/not-zip-safe
pyramid_dogpile_cache.egg-info/requires.txt
pyramid_dogpile_cache.egg-info/top_level.txt