Metadata-Version: 1.1
Name: pyramid-dogpile-cache
Version: 0.0.4
Summary: dogpile.cache factory for Pyramid
Home-page: https://github.com/moriyoshi/pyramid_dogpile_cache
Author: Moriyoshi Koizumi
Author-email: mozo@mozo.jp
License: mit
Keywords: web wsgi pylons pyramid dogpile cache
Platform: UNKNOWN
Classifier: Intended Audience :: Developers
Classifier: License :: OSI Approved :: MIT License
Classifier: Operating System :: OS Independent
Classifier: Programming Language :: Python
Classifier: Programming Language :: Python :: 2
Classifier: Programming Language :: Python :: 2.6
Classifier: Programming Language :: Python :: 2.7
Classifier: Programming Language :: Python :: 3
Classifier: Programming Language :: Python :: 3.2
Classifier: Programming Language :: Python :: 3.3
Classifier: Programming Language :: Python :: 3.4
Classifier: Programming Language :: Python :: Implementation :: CPython
Classifier: Programming Language :: Python :: Implementation :: PyPy
Classifier: Framework :: Pyramid
